torso_mapper/__init__.py
torso_mapper/analyzer.py
torso_mapper/cli.py
torso_mapper/data/__init__.py
torso_mapper/data/auto_trim.py
torso_mapper/data/dataset.py
torso_mapper/data/folder_dataset.py
torso_mapper/data/utils.py
torso_mapper/model/__init__.py
torso_mapper/model/block.py
torso_mapper/model/conv_3d_net.py
torso_mapper/model/resnet_block.py
torso_mapper/results/__init__.py
torso_mapper/results/result_tracker.py
torso_mapper/results/scan_result.py
torso_mapper/utils/__init__py
torso_mapper/utils/plotting.py
torso_mapper-1.0.2.dist-info/LICENSE
torso_mapper-1.0.2.dist-info/METADATA
torso_mapper-1.0.2.dist-info/WHEEL
torso_mapper-1.0.2.dist-info/entry_points.txt
torso_mapper-1.0.2.dist-info/RECORD
