Metadata-Version: 2.1
Name: torso_mapper
Version: 1.0.2
Summary: A package for quickly identifying part of the torso imaged an CT scan throught visible vertebrae
License: MIT
Author: Marius Urbonas
Requires-Python: >=3.10,<4.0
Classifier: License :: OSI Approved :: MIT License
Classifier: Programming Language :: Python :: 3
Classifier: Programming Language :: Python :: 3.10
Classifier: Programming Language :: Python :: 3.11
Classifier: Programming Language :: Python :: 3.12
Requires-Dist: click (>=8.1.7,<9.0.0)
Requires-Dist: nibabel (>=5.2.1,<6.0.0)
Requires-Dist: pytest (>=8.3.3,<9.0.0)
Requires-Dist: scipy (>=1.14.0,<2.0.0)
Requires-Dist: torch (>=2.3.1,<3.0.0)
Requires-Dist: transformers (>=4.42.4,<5.0.0)
